{
  "$schema": "https://json.schemastore.org/tsconfig",
  "display": "Default",
  "compilerOptions": {
    "allowImportingTsExtensions": true,
    "allowSyntheticDefaultImports": true,
    "composite": false,
    "declaration": true,
    "declarationMap": true,
    "esModuleInterop": true,
    "forceConsistentCasingInFileNames": true,
    "inlineSources": false,
    "isolatedModules": true,
    "lib": ["DOM", "DOM.Iterable", "ESNext", "WebWorker"],
    "module": "ESNext",
    "moduleResolution": "bundler",
    "noEmit": true,
    "noUncheckedIndexedAccess": true,
    "noUnusedLocals": false,
    "noUnusedParameters": false,
    "preserveWatchOutput": true,
    "skipLibCheck": true,
    "strict": true,
    "target": "ESNext"
  },
  "exclude": ["**/node_modules", "**/dist", "**/build", "**/coverage", "**/output", "**/storybook-static", "**/.junit"]
}
